[{"id":97,"count":16,"description":"","link":"https:\/\/hyp3rids.com\/archives\/category\/blog-green","name":"Blog Green","slug":"blog-green","taxonomy":"category","parent":0,"meta":[],"_links":{"self":[{"href":"https:\/\/hyp3rids.com\/wp-json\/wp\/v2\/categories\/97","targetHints":{"allow":["GET"]}}],"collection":[{"href":"https:\/\/hyp3rids.com\/wp-json\/wp\/v2\/categories"}],"about":[{"href":"https:\/\/hyp3rids.com\/wp-json\/wp\/v2\/taxonomies\/category"}],"wp:post_type":[{"href":"https:\/\/hyp3rids.com\/wp-json\/wp\/v2\/posts?categories=97"}],"curies":[{"name":"wp","href":"https:\/\/api.w.org\/{rel}","templated":true}]}},{"id":42,"count":8,"description":"","link":"https:\/\/hyp3rids.com\/archives\/category\/blog-masonry","name":"Blog masonry","slug":"blog-masonry","taxonomy":"category","parent":0,"meta":[],"_links":{"self":[{"href":"https:\/\/hyp3rids.com\/wp-json\/wp\/v2\/categories\/42","targetHints":{"allow":["GET"]}}],"collection":[{"href":"https:\/\/hyp3rids.com\/wp-json\/wp\/v2\/categories"}],"about":[{"href":"https:\/\/hyp3rids.com\/wp-json\/wp\/v2\/taxonomies\/category"}],"wp:post_type":[{"href":"https:\/\/hyp3rids.com\/wp-json\/wp\/v2\/posts?categories=42"}],"curies":[{"name":"wp","href":"https:\/\/api.w.org\/{rel}","templated":true}]}},{"id":48,"count":7,"description":"","link":"https:\/\/hyp3rids.com\/archives\/category\/blog-with-scroll","name":"Blog with scroll","slug":"blog-with-scroll","taxonomy":"category","parent":0,"meta":[],"_links":{"self":[{"href":"https:\/\/hyp3rids.com\/wp-json\/wp\/v2\/categories\/48","targetHints":{"allow":["GET"]}}],"collection":[{"href":"https:\/\/hyp3rids.com\/wp-json\/wp\/v2\/categories"}],"about":[{"href":"https:\/\/hyp3rids.com\/wp-json\/wp\/v2\/taxonomies\/category"}],"wp:post_type":[{"href":"https:\/\/hyp3rids.com\/wp-json\/wp\/v2\/posts?categories=48"}],"curies":[{"name":"wp","href":"https:\/\/api.w.org\/{rel}","templated":true}]}},{"id":50,"count":2,"description":"","link":"https:\/\/hyp3rids.com\/archives\/category\/choise","name":"Choise","slug":"choise","taxonomy":"category","parent":0,"meta":[],"_links":{"self":[{"href":"https:\/\/hyp3rids.com\/wp-json\/wp\/v2\/categories\/50","targetHints":{"allow":["GET"]}}],"collection":[{"href":"https:\/\/hyp3rids.com\/wp-json\/wp\/v2\/categories"}],"about":[{"href":"https:\/\/hyp3rids.com\/wp-json\/wp\/v2\/taxonomies\/category"}],"wp:post_type":[{"href":"https:\/\/hyp3rids.com\/wp-json\/wp\/v2\/posts?categories=50"}],"curies":[{"name":"wp","href":"https:\/\/api.w.org\/{rel}","templated":true}]}},{"id":49,"count":1,"description":"","link":"https:\/\/hyp3rids.com\/archives\/category\/mobile","name":"Mobile","slug":"mobile","taxonomy":"category","parent":0,"meta":[],"_links":{"self":[{"href":"https:\/\/hyp3rids.com\/wp-json\/wp\/v2\/categories\/49","targetHints":{"allow":["GET"]}}],"collection":[{"href":"https:\/\/hyp3rids.com\/wp-json\/wp\/v2\/categories"}],"about":[{"href":"https:\/\/hyp3rids.com\/wp-json\/wp\/v2\/taxonomies\/category"}],"wp:post_type":[{"href":"https:\/\/hyp3rids.com\/wp-json\/wp\/v2\/posts?categories=49"}],"curies":[{"name":"wp","href":"https:\/\/api.w.org\/{rel}","templated":true}]}},{"id":51,"count":3,"description":"","link":"https:\/\/hyp3rids.com\/archives\/category\/photographers","name":"Photographers","slug":"photographers","taxonomy":"category","parent":0,"meta":[],"_links":{"self":[{"href":"https:\/\/hyp3rids.com\/wp-json\/wp\/v2\/categories\/51","targetHints":{"allow":["GET"]}}],"collection":[{"href":"https:\/\/hyp3rids.com\/wp-json\/wp\/v2\/categories"}],"about":[{"href":"https:\/\/hyp3rids.com\/wp-json\/wp\/v2\/taxonomies\/category"}],"wp:post_type":[{"href":"https:\/\/hyp3rids.com\/wp-json\/wp\/v2\/posts?categories=51"}],"curies":[{"name":"wp","href":"https:\/\/api.w.org\/{rel}","templated":true}]}},{"id":44,"count":11,"description":"","link":"https:\/\/hyp3rids.com\/archives\/category\/squares","name":"Squares","slug":"squares","taxonomy":"category","parent":0,"meta":[],"_links":{"self":[{"href":"https:\/\/hyp3rids.com\/wp-json\/wp\/v2\/categories\/44","targetHints":{"allow":["GET"]}}],"collection":[{"href":"https:\/\/hyp3rids.com\/wp-json\/wp\/v2\/categories"}],"about":[{"href":"https:\/\/hyp3rids.com\/wp-json\/wp\/v2\/taxonomies\/category"}],"wp:post_type":[{"href":"https:\/\/hyp3rids.com\/wp-json\/wp\/v2\/posts?categories=44"}],"curies":[{"name":"wp","href":"https:\/\/api.w.org\/{rel}","templated":true}]}},{"id":1,"count":3,"description":"","link":"https:\/\/hyp3rids.com\/archives\/category\/uncategorized","name":"Uncategorized","slug":"uncategorized","taxonomy":"category","parent":0,"meta":[],"_links":{"self":[{"href":"https:\/\/hyp3rids.com\/wp-json\/wp\/v2\/categories\/1","targetHints":{"allow":["GET"]}}],"collection":[{"href":"https:\/\/hyp3rids.com\/wp-json\/wp\/v2\/categories"}],"about":[{"href":"https:\/\/hyp3rids.com\/wp-json\/wp\/v2\/taxonomies\/category"}],"wp:post_type":[{"href":"https:\/\/hyp3rids.com\/wp-json\/wp\/v2\/posts?categories=1"}],"curies":[{"name":"wp","href":"https:\/\/api.w.org\/{rel}","templated":true}]}}]
